Metadata-Version: 2.1
Name: biliLive
Version: 0.3.0
Summary: bilibili Python 弹幕机
Home-page: https://github.com/FengLiuFeseliud/biliLive
Author: FengLiuFeseliud
Author-email: 17351198406@qq.com
License: UNKNOWN
Platform: any
Classifier: Programming Language :: Python :: 3
Classifier: License :: OSI Approved :: MIT License
Classifier: Operating System :: OS Independent
Requires-Python: >=3.7
License-File: LICENSE
